LICENSE
README.md
setup.py
Cipher/__init__.py
Cipher/main.py
Cipher/test.py
CipherProgram.egg-info/PKG-INFO
CipherProgram.egg-info/SOURCES.txt
CipherProgram.egg-info/dependency_links.txt
CipherProgram.egg-info/top_level.txt