Metadata-Version: 2.1
Name: CipherProgram
Version: 0.0.4
Home-page: https://github.com/Cipher58/
Download-URL: https://github.com/Cipher58/Cipher.git
Author: Cipher58
Author-email: cipher58public@gmail.com
License: The Unlicense
Classifier: Programming Language :: Python :: 3
Classifier: Operating System :: OS Independent
License-File: LICENSE
